sec_html_parser/__init__.py
sec_html_parser/__main__.py
sec_html_parser/div_style.py
sec_html_parser/parser.py
sec_html_parser/span_style.py
sec_html_parser-0.3.1.dist-info/WHEEL
sec_html_parser-0.3.1.dist-info/METADATA
sec_html_parser-0.3.1.dist-info/RECORD
