Metadata-Version: 2.1
Name: sec-html-parser
Version: 0.3.1
Summary: Simple library for parsing SEC forms
Author: Tom Selfin
Author-email: selfint@gmail.com
Requires-Python: >=3.9,<4.0
Classifier: Programming Language :: Python :: 3
Classifier: Programming Language :: Python :: 3.9
Requires-Dist: beautifulsoup4 (>=4.9.3,<5.0.0)
Requires-Dist: click (>=8.0.1,<9.0.0)
